siwe_auth/__init__.py
siwe_auth/admin.py
siwe_auth/apps.py
siwe_auth/backends.py
siwe_auth/conf.py
siwe_auth/constants.py
siwe_auth/groups.py
siwe_auth/models.py
siwe_auth/urls.py
siwe_auth/utils.py
siwe_auth/views.py
siwe_auth/migrations/0001_initial.py
siwe_auth/migrations/__init__.py
siwe_auth_django-3.0.3.dist-info/METADATA
siwe_auth_django-3.0.3.dist-info/WHEEL
siwe_auth_django-3.0.3.dist-info/licenses/LICENSE
siwe_auth_django-3.0.3.dist-info/RECORD
