Metadata-Version: 2.1
Name: siwe-auth-django
Version: 3.0.3
Summary: Custom Django authentication backend using Sign-In with Ethereum (EIP-4361) with a custom wallet user model. Available to use in django rest api or django app.
Project-URL: Homepage, https://github.com/giovaborgogno/siwe-auth-django
Project-URL: Repository, https://github.com/giovaborgogno/siwe-auth-django
Project-URL: Issues, https://github.com/giovaborgogno/siwe-auth-django/issues
Author-email: Giovanni Borgogno <giovaborgogno@gmail.com>
License: MIT License
License-File: LICENSE
Keywords: Authentication,Authorization,Django,EIP-4361,SIWE,Sign-In with Ethereum,Web3
Classifier: License :: OSI Approved :: MIT License
Classifier: Operating System :: OS Independent
Classifier: Programming Language :: Python :: 3
Requires-Python: >=3.8
Requires-Dist: django>=3.0
Requires-Dist: pytz
Requires-Dist: siwe==2.4.1
Requires-Dist: web3>=6.0.0
